{
    "businesses": [
        {
            "id": "KdH4w6BAc9ckVNZpyd4xWg",
            "alias": "mattina-san-francisco",
            "name": "Mattina",
            "image_url": "https://s3-media4.fl.yelpcdn.com/bphoto/FyWIR_GZN3uhOb3m02F50w/o.jpg",
            "is_closed": false,
            "url": "https://www.yelp.com/biz/mattina-san-francisco?adjust_creative=dMEMCWkbmi2hzr24_9J-ZA&utm_campaign=yelp_api_v3&utm_medium=api_v3_business_search&utm_source=dMEMCWkbmi2hzr24_9J-ZA",
            "review_count": 23,
            "categories": [
                {
                    "alias": "italian",
                    "title": "Italian"
                },
                {
                    "alias": "coffee",
                    "title": "Coffee & Tea"
                },
                {
                    "alias": "breakfast_brunch",
                    "title": "Breakfast & Brunch"
                }
            ],
            "rating": 4.0,
            "coordinates": {
                "latitude": 37.787223387923554,
                "longitude": -122.4341518
            },
            "transactions": [],
            "location": {
                "address1": "2232 Bush St",
                "address2": "",
                "address3": null,
                "city": "San Francisco",
                "zip_code": "94115",
                "country": "US",
                "state": "CA",
                "display_address": [
                    "2232 Bush St",
                    "San Francisco, CA 94115"
                ]
            },
            "phone": "",
            "display_phone": "",
            "distance": 2934.03584491675
        },
        {
            "id": "s2R3RUJ09eBFvHVIUS4Shg",
            "alias": "kothai-republic-san-francisco",
            "name": "Kothai Republic",
            "image_url": "https://s3-media4.fl.yelpcdn.com/bphoto/9NPm_CSb_jKbVuOkuhEvRw/o.jpg",
            "is_closed": false,
            "url": "https://www.yelp.com/biz/kothai-republic-san-francisco?adjust_creative=dMEMCWkbmi2hzr24_9J-ZA&utm_campaign=yelp_api_v3&utm_medium=api_v3_business_search&utm_source=dMEMCWkbmi2hzr24_9J-ZA",
            "review_count": 133,
            "categories": [
                {
                    "alias": "korean",
                    "title": "Korean"
                },
                {
                    "alias": "thai",
                    "title": "Thai"
                },
                {
                    "alias": "noodles",
                    "title": "Noodles"
                }
            ],
            "rating": 4.5,
            "coordinates": {
                "latitude": 37.76219,
                "longitude": -122.46604
            },
            "transactions": [],
            "location": {
                "address1": "1398 9th Ave",
                "address2": null,
                "address3": "",
                "city": "San Francisco",
                "zip_code": "94122",
                "country": "US",
                "state": "CA",
                "display_address": [
                    "1398 9th Ave",
                    "San Francisco, CA 94122"
                ]
            },
            "phone": "+14157424058",
            "display_phone": "(415) 742-4058",
            "distance": 2606.5969287543485
        },
        {
            "id": "4jqo3BvBEiNrvLKJW41Qbg",
            "alias": "the-public-izakaya-san-francisco",
            "name": "The Public Izakaya",
            "image_url": "https://s3-media2.fl.yelpcdn.com/bphoto/5wSMYm8s6Z_OSXI5rRxWIQ/o.jpg",
            "is_closed": false,
            "url": "https://www.yelp.com/biz/the-public-izakaya-san-francisco?adjust_creative=dMEMCWkbmi2hzr24_9J-ZA&utm_campaign=yelp_api_v3&utm_medium=api_v3_business_search&utm_source=dMEMCWkbmi2hzr24_9J-ZA",
            "review_count": 253,
            "categories": [
                {
                    "alias": "izakaya",
                    "title": "Izakaya"
                },
                {
                    "alias": "sushi",
                    "title": "Sushi Bars"
                },
                {
                    "alias": "ramen",
                    "title": "Ramen"
                }
            ],
            "rating": 4.5,
            "coordinates": {
                "latitude": 37.787836462530876,
                "longitude": -122.413599
            },
            "transactions": [],
            "price": "$$",
            "location": {
                "address1": "700 Post St",
                "address2": null,
                "address3": "",
                "city": "San Francisco",
                "zip_code": "94109",
                "country": "US",
                "state": "CA",
                "display_address": [
                    "700 Post St",
                    "San Francisco, CA 94109"
                ]
            },
            "phone": "+14156587588",
            "display_phone": "(415) 658-7588",
            "distance": 3606.1481462817164
        },
        {
            "id": "qcTW3btfGVVnQQ3DG3KwdQ",
            "alias": "la-sarrasine-san-francisco-2",
            "name": "La Sarrasine",
            "image_url": "https://s3-media4.fl.yelpcdn.com/bphoto/AAWmxGiwH2uJwbM643lWzA/o.jpg",
            "is_closed": false,
            "url": "https://www.yelp.com/biz/la-sarrasine-san-francisco-2?adjust_creative=dMEMCWkbmi2hzr24_9J-ZA&utm_campaign=yelp_api_v3&utm_medium=api_v3_business_search&utm_source=dMEMCWkbmi2hzr24_9J-ZA",
            "review_count": 14,
            "categories": [
                {
                    "alias": "creperies",
                    "title": "Creperies"
                },
                {
                    "alias": "breakfast_brunch",
                    "title": "Breakfast & Brunch"
                },
                {
                    "alias": "tradamerican",
                    "title": "American (Traditional)"
                }
            ],
            "rating": 4.5,
            "coordinates": {
                "latitude": 37.775244759082085,
                "longitude": -122.4380604766232
            },
            "transactions": [
                "delivery",
                "pickup"
            ],
            "location": {
                "address1": "607 Divisadero St",
                "address2": "",
                "address3": null,
                "city": "San Francisco",
                "zip_code": "94117",
                "country": "US",
                "state": "CA",
                "display_address": [
                    "607 Divisadero St",
                    "San Francisco, CA 94117"
                ]
            },
            "phone": "+14154174915",
            "display_phone": "(415) 417-4915",
            "distance": 1601.42174271267
        },
        {
            "id": "_hOVIgjVRl_HzvLaa65KJg",
            "alias": "the-snug-san-francisco",
            "name": "The Snug",
            "image_url": "https://s3-media3.fl.yelpcdn.com/bphoto/MutHRQoBt5krVldjIK88IA/o.jpg",
            "is_closed": false,
            "url": "https://www.yelp.com/biz/the-snug-san-francisco?adjust_creative=dMEMCWkbmi2hzr24_9J-ZA&utm_campaign=yelp_api_v3&utm_medium=api_v3_business_search&utm_source=dMEMCWkbmi2hzr24_9J-ZA",
            "review_count": 394,
            "categories": [
                {
                    "alias": "cocktailbars",
                    "title": "Cocktail Bars"
                },
                {
                    "alias": "newamerican",
                    "title": "American (New)"
                }
            ],
            "rating": 4.0,
            "coordinates": {
                "latitude": 37.79094,
                "longitude": -122.43443
            },
            "transactions": [
                "delivery"
            ],
            "price": "$$",
            "location": {
                "address1": "2301 Fillmore St",
                "address2": "",
                "address3": null,
                "city": "San Francisco",
                "zip_code": "94115",
                "country": "US",
                "state": "CA",
                "display_address": [
                    "2301 Fillmore St",
                    "San Francisco, CA 94115"
                ]
            },
            "phone": "",
            "display_phone": "",
            "distance": 3333.338457427281
        },
        {
            "id": "HHtpR0RslupSQ99GIIwW5A",
            "alias": "marufuku-ramen-san-francisco-5",
            "name": "Marufuku Ramen",
            "image_url": "https://s3-media4.fl.yelpcdn.com/bphoto/ouK2VmW0SrI70jsJpTxJhw/o.jpg",
            "is_closed": false,
            "url": "https://www.yelp.com/biz/marufuku-ramen-san-francisco-5?adjust_creative=dMEMCWkbmi2hzr24_9J-ZA&utm_campaign=yelp_api_v3&utm_medium=api_v3_business_search&utm_source=dMEMCWkbmi2hzr24_9J-ZA",
            "review_count": 4587,
            "categories": [
                {
                    "alias": "ramen",
                    "title": "Ramen"
                }
            ],
            "rating": 4.5,
            "coordinates": {
                "latitude": 37.785014,
                "longitude": -122.431842
            },
            "transactions": [
                "delivery",
                "pickup"
            ],
            "price": "$$",
            "location": {
                "address1": "1581 Webster St",
                "address2": "Ste 235",
                "address3": null,
                "city": "San Francisco",
                "zip_code": "94115",
                "country": "US",
                "state": "CA",
                "display_address": [
                    "1581 Webster St",
                    "Ste 235",
                    "San Francisco, CA 94115"
                ]
            },
            "phone": "+14158729786",
            "display_phone": "(415) 872-9786",
            "distance": 2717.1759329403035
        },
        {
            "id": "6YuJE0vjUpIzYckRMnzy0g",
            "alias": "savor-san-francisco-7",
            "name": "Savor",
            "image_url": "https://s3-media1.fl.yelpcdn.com/bphoto/bskdpiM9uOzPvJ5-v7HNRQ/o.jpg",
            "is_closed": false,
            "url": "https://www.yelp.com/biz/savor-san-francisco-7?adjust_creative=dMEMCWkbmi2hzr24_9J-ZA&utm_campaign=yelp_api_v3&utm_medium=api_v3_business_search&utm_source=dMEMCWkbmi2hzr24_9J-ZA",
            "review_count": 136,
            "categories": [
                {
                    "alias": "mediterranean",
                    "title": "Mediterranean"
                },
                {
                    "alias": "vegetarian",
                    "title": "Vegetarian"
                },
                {
                    "alias": "vegan",
                    "title": "Vegan"
                }
            ],
            "rating": 4.5,
            "coordinates": {
                "latitude": 37.76411439958351,
                "longitude": -122.46223150576381
            },
            "transactions": [
                "delivery",
                "pickup",
                "restaurant_reservation"
            ],
            "price": "$$",
            "location": {
                "address1": "401 Irving St",
                "address2": "",
                "address3": null,
                "city": "San Francisco",
                "zip_code": "94122",
                "country": "US",
                "state": "CA",
                "display_address": [
                    "401 Irving St",
                    "San Francisco, CA 94122"
                ]
            },
            "phone": "+14157026048",
            "display_phone": "(415) 702-6048",
            "distance": 2294.6117406979715
        },
        {
            "id": "8VurRDEj1RpimenhgTmyFQ",
            "alias": "kaiy\u014d-rooftop-san-francisco-5",
            "name": "KAIY\u014c Rooftop",
            "image_url": "https://s3-media4.fl.yelpcdn.com/bphoto/IpnkGDpsm94wGzTAdFekPg/o.jpg",
            "is_closed": false,
            "url": "https://www.yelp.com/biz/kaiy%C5%8D-rooftop-san-francisco-5?adjust_creative=dMEMCWkbmi2hzr24_9J-ZA&utm_campaign=yelp_api_v3&utm_medium=api_v3_business_search&utm_source=dMEMCWkbmi2hzr24_9J-ZA",
            "review_count": 568,
            "categories": [
                {
                    "alias": "peruvian",
                    "title": "Peruvian"
                },
                {
                    "alias": "cocktailbars",
                    "title": "Cocktail Bars"
                },
                {
                    "alias": "sushi",
                    "title": "Sushi Bars"
                }
            ],
            "rating": 4.0,
            "coordinates": {
                "latitude": 37.77882,
                "longitude": -122.3924
            },
            "transactions": [],
            "location": {
                "address1": "701 3rd St",
                "address2": "Fl 12",
                "address3": "",
                "city": "San Francisco",
                "zip_code": "94105",
                "country": "US",
                "state": "CA",
                "display_address": [
                    "701 3rd St",
                    "Fl 12",
                    "San Francisco, CA 94105"
                ]
            },
            "phone": "+14158008141",
            "display_phone": "(415) 800-8141",
            "distance": 4355.096615628698
        },
        {
            "id": "GDlwI_lXMQN0IInysFIarQ",
            "alias": "best-kept-secret-san-francisco",
            "name": "Best Kept Secret",
            "image_url": "https://s3-media2.fl.yelpcdn.com/bphoto/tpTcZhqJLglcfc6e65tl2A/o.jpg",
            "is_closed": false,
            "url": "https://www.yelp.com/biz/best-kept-secret-san-francisco?adjust_creative=dMEMCWkbmi2hzr24_9J-ZA&utm_campaign=yelp_api_v3&utm_medium=api_v3_business_search&utm_source=dMEMCWkbmi2hzr24_9J-ZA",
            "review_count": 37,
            "categories": [
                {
                    "alias": "lounges",
                    "title": "Lounges"
                },
                {
                    "alias": "cocktailbars",
                    "title": "Cocktail Bars"
                },
                {
                    "alias": "breakfast_brunch",
                    "title": "Breakfast & Brunch"
                }
            ],
            "rating": 4.5,
            "coordinates": {
                "latitude": 37.742763,
                "longitude": -122.477599
            },
            "transactions": [],
            "price": "$$",
            "location": {
                "address1": "1055 Taraval St",
                "address2": "",
                "address3": null,
                "city": "San Francisco",
                "zip_code": "94116",
                "country": "US",
                "state": "CA",
                "display_address": [
                    "1055 Taraval St",
                    "San Francisco, CA 94116"
                ]
            },
            "phone": "+14155988220",
            "display_phone": "(415) 598-8220",
            "distance": 4145.65507752923
        },
        {
            "id": "QueFVMcMlT-6aZFv2M47mg",
            "alias": "bottega-san-francisco-2",
            "name": "Bottega",
            "image_url": "https://s3-media2.fl.yelpcdn.com/bphoto/IawDcF1QmHSzUQDczHYVuw/o.jpg",
            "is_closed": false,
            "url": "https://www.yelp.com/biz/bottega-san-francisco-2?adjust_creative=dMEMCWkbmi2hzr24_9J-ZA&utm_campaign=yelp_api_v3&utm_medium=api_v3_business_search&utm_source=dMEMCWkbmi2hzr24_9J-ZA",
            "review_count": 737,
            "categories": [
                {
                    "alias": "italian",
                    "title": "Italian"
                },
                {
                    "alias": "pastashops",
                    "title": "Pasta Shops"
                },
                {
                    "alias": "pizza",
                    "title": "Pizza"
                }
            ],
            "rating": 4.5,
            "coordinates": {
                "latitude": 37.75472,
                "longitude": -122.4212
            },
            "transactions": [
                "delivery",
                "pickup"
            ],
            "price": "$$",
            "location": {
                "address1": "1132 Valencia St",
                "address2": null,
                "address3": "",
                "city": "San Francisco",
                "zip_code": "94110",
                "country": "US",
                "state": "CA",
                "display_address": [
                    "1132 Valencia St",
                    "San Francisco, CA 94110"
                ]
            },
            "phone": "+14156559048",
            "display_phone": "(415) 655-9048",
            "distance": 1506.2503434999724
        },
        {
            "id": "J7_-faNq_Ag9qTOlDn81Pw",
            "alias": "starbelly-san-francisco",
            "name": "Starbelly",
            "image_url": "https://s3-media2.fl.yelpcdn.com/bphoto/G1SweY3VbKx_BqAws9RytA/o.jpg",
            "is_closed": false,
            "url": "https://www.yelp.com/biz/starbelly-san-francisco?adjust_creative=dMEMCWkbmi2hzr24_9J-ZA&utm_campaign=yelp_api_v3&utm_medium=api_v3_business_search&utm_source=dMEMCWkbmi2hzr24_9J-ZA",
            "review_count": 2223,
            "categories": [
                {
                    "alias": "newamerican",
                    "title": "American (New)"
                },
                {
                    "alias": "breakfast_brunch",
                    "title": "Breakfast & Brunch"
                },
                {
                    "alias": "cocktailbars",
                    "title": "Cocktail Bars"
                }
            ],
            "rating": 4.0,
            "coordinates": {
                "latitude": 37.76402,
                "longitude": -122.43253
            },
            "transactions": [
                "delivery",
                "pickup",
                "restaurant_reservation"
            ],
            "price": "$$",
            "location": {
                "address1": "3583 16th St",
                "address2": "",
                "address3": "",
                "city": "San Francisco",
                "zip_code": "94114",
                "country": "US",
                "state": "CA",
                "display_address": [
                    "3583 16th St",
                    "San Francisco, CA 94114"
                ]
            },
            "phone": "+14152527500",
            "display_phone": "(415) 252-7500",
            "distance": 490.0201155034338
        },
        {
            "id": "d5752S_RDb26HxoL6O06eQ",
            "alias": "beit-rima-san-francisco-4",
            "name": "Beit Rima",
            "image_url": "https://s3-media4.fl.yelpcdn.com/bphoto/Rtlt_dnu7r-fRl579Zyl7w/o.jpg",
            "is_closed": false,
            "url": "https://www.yelp.com/biz/beit-rima-san-francisco-4?adjust_creative=dMEMCWkbmi2hzr24_9J-ZA&utm_campaign=yelp_api_v3&utm_medium=api_v3_business_search&utm_source=dMEMCWkbmi2hzr24_9J-ZA",
            "review_count": 253,
            "categories": [
                {
                    "alias": "arabian",
                    "title": "Arabic"
                },
                {
                    "alias": "mediterranean",
                    "title": "Mediterranean"
                },
                {
                    "alias": "lebanese",
                    "title": "Lebanese"
                }
            ],
            "rating": 4.5,
            "coordinates": {
                "latitude": 37.765956,
                "longitude": -122.449679
            },
            "transactions": [],
            "price": "$$",
            "location": {
                "address1": "86 Carl St",
                "address2": "",
                "address3": null,
                "city": "San Francisco",
                "zip_code": "94117",
                "country": "US",
                "state": "CA",
                "display_address": [
                    "86 Carl St",
                    "San Francisco, CA 94117"
                ]
            },
            "phone": "+14155661274",
            "display_phone": "(415) 566-1274",
            "distance": 1291.888183200842
        },
        {
            "id": "D26qBnudK_1pdo6AlvMlvQ",
            "alias": "otra-san-francisco-3",
            "name": "Otra",
            "image_url": "https://s3-media1.fl.yelpcdn.com/bphoto/GARvNjf2fbdvR4oL4UiZWg/o.jpg",
            "is_closed": false,
            "url": "https://www.yelp.com/biz/otra-san-francisco-3?adjust_creative=dMEMCWkbmi2hzr24_9J-ZA&utm_campaign=yelp_api_v3&utm_medium=api_v3_business_search&utm_source=dMEMCWkbmi2hzr24_9J-ZA",
            "review_count": 141,
            "categories": [
                {
                    "alias": "mexican",
                    "title": "Mexican"
                },
                {
                    "alias": "cocktailbars",
                    "title": "Cocktail Bars"
                }
            ],
            "rating": 4.5,
            "coordinates": {
                "latitude": 37.771842,
                "longitude": -122.433369
            },
            "transactions": [],
            "location": {
                "address1": "682 Haight St",
                "address2": null,
                "address3": "",
                "city": "San Francisco",
                "zip_code": "94117",
                "country": "US",
                "state": "CA",
                "display_address": [
                    "682 Haight St",
                    "San Francisco, CA 94117"
                ]
            },
            "phone": "+14155002774",
            "display_phone": "(415) 500-2774",
            "distance": 1253.8422059936656
        },
        {
            "id": "MaaySW1ejpwQCkr9jn1glA",
            "alias": "the-tailors-son-san-francisco",
            "name": "The Tailor's Son",
            "image_url": "https://s3-media2.fl.yelpcdn.com/bphoto/P4NfQ7KFvHpcfBcOwxBZJA/o.jpg",
            "is_closed": false,
            "url": "https://www.yelp.com/biz/the-tailors-son-san-francisco?adjust_creative=dMEMCWkbmi2hzr24_9J-ZA&utm_campaign=yelp_api_v3&utm_medium=api_v3_business_search&utm_source=dMEMCWkbmi2hzr24_9J-ZA",
            "review_count": 422,
            "categories": [
                {
                    "alias": "italian",
                    "title": "Italian"
                },
                {
                    "alias": "cocktailbars",
                    "title": "Cocktail Bars"
                }
            ],
            "rating": 4.0,
            "coordinates": {
                "latitude": 37.788589,
                "longitude": -122.434054
            },
            "transactions": [
                "restaurant_reservation"
            ],
            "location": {
                "address1": "2049 Fillmore St",
                "address2": "",
                "address3": null,
                "city": "San Francisco",
                "zip_code": "94115",
                "country": "US",
                "state": "CA",
                "display_address": [
                    "2049 Fillmore St",
                    "San Francisco, CA 94115"
                ]
            },
            "phone": "+14156737200",
            "display_phone": "(415) 673-7200",
            "distance": 3088.5469839843977
        },
        {
            "id": "kvrQecqdGvnuVICMstZJmA",
            "alias": "dumpling-home-san-francisco",
            "name": "Dumpling Home",
            "image_url": "https://s3-media3.fl.yelpcdn.com/bphoto/Utdv29yFK-sfp9D1Tg-Bwg/o.jpg",
            "is_closed": false,
            "url": "https://www.yelp.com/biz/dumpling-home-san-francisco?adjust_creative=dMEMCWkbmi2hzr24_9J-ZA&utm_campaign=yelp_api_v3&utm_medium=api_v3_business_search&utm_source=dMEMCWkbmi2hzr24_9J-ZA",
            "review_count": 993,
            "categories": [
                {
                    "alias": "dimsum",
                    "title": "Dim Sum"
                },
                {
                    "alias": "noodles",
                    "title": "Noodles"
                },
                {
                    "alias": "asianfusion",
                    "title": "Asian Fusion"
                }
            ],
            "rating": 4.5,
            "coordinates": {
                "latitude": 37.775830550017254,
                "longitude": -122.4226361
            },
            "transactions": [
                "delivery",
                "pickup"
            ],
            "price": "$$",
            "location": {
                "address1": "298 Gough St",
                "address2": "",
                "address3": null,
                "city": "San Francisco",
                "zip_code": "94102",
                "country": "US",
                "state": "CA",
                "display_address": [
                    "298 Gough St",
                    "San Francisco, CA 94102"
                ]
            },
            "phone": "+14155031666",
            "display_phone": "(415) 503-1666",
            "distance": 2056.7497118286074
        },
        {
            "id": "8dUaybEPHsZMgr1iKgqgMQ",
            "alias": "sotto-mare-san-francisco-4",
            "name": "Sotto Mare",
            "image_url": "https://s3-media3.fl.yelpcdn.com/bphoto/o3hIcGLMxV_5ynxEjGWGrw/o.jpg",
            "is_closed": false,
            "url": "https://www.yelp.com/biz/sotto-mare-san-francisco-4?adjust_creative=dMEMCWkbmi2hzr24_9J-ZA&utm_campaign=yelp_api_v3&utm_medium=api_v3_business_search&utm_source=dMEMCWkbmi2hzr24_9J-ZA",
            "review_count": 4943,
            "categories": [
                {
                    "alias": "seafood",
                    "title": "Seafood"
                },
                {
                    "alias": "italian",
                    "title": "Italian"
                },
                {
                    "alias": "bars",
                    "title": "Bars"
                }
            ],
            "rating": 4.5,
            "coordinates": {
                "latitude": 37.79979,
                "longitude": -122.40834
            },
            "transactions": [
                "delivery",
                "pickup"
            ],
            "price": "$$",
            "location": {
                "address1": "552 Green St",
                "address2": "",
                "address3": "",
                "city": "San Francisco",
                "zip_code": "94133",
                "country": "US",
                "state": "CA",
                "display_address": [
                    "552 Green St",
                    "San Francisco, CA 94133"
                ]
            },
            "phone": "+14153983181",
            "display_phone": "(415) 398-3181",
            "distance": 4970.484877370465
        },
        {
            "id": "f-m7-hyFzkf0HSEeQ2s-9A",
            "alias": "fog-harbor-fish-house-san-francisco-2",
            "name": "Fog Harbor Fish House",
            "image_url": "https://s3-media2.fl.yelpcdn.com/bphoto/by8Hh63BLPv_HUqRUdsp_w/o.jpg",
            "is_closed": false,
            "url": "https://www.yelp.com/biz/fog-harbor-fish-house-san-francisco-2?adjust_creative=dMEMCWkbmi2hzr24_9J-ZA&utm_campaign=yelp_api_v3&utm_medium=api_v3_business_search&utm_source=dMEMCWkbmi2hzr24_9J-ZA",
            "review_count": 9309,
            "categories": [
                {
                    "alias": "seafood",
                    "title": "Seafood"
                },
                {
                    "alias": "wine_bars",
                    "title": "Wine Bars"
                },
                {
                    "alias": "cocktailbars",
                    "title": "Cocktail Bars"
                }
            ],
            "rating": 4.5,
            "coordinates": {
                "latitude": 37.80898821475503,
                "longitude": -122.41029651587517
            },
            "transactions": [
                "restaurant_reservation"
            ],
            "price": "$$",
            "location": {
                "address1": "39 Pier",
                "address2": "Ste a - 202",
                "address3": "",
                "city": "San Francisco",
                "zip_code": "94133",
                "country": "US",
                "state": "CA",
                "display_address": [
                    "39 Pier",
                    "Ste a - 202",
                    "San Francisco, CA 94133"
                ]
            },
            "phone": "+14159692010",
            "display_phone": "(415) 969-2010",
            "distance": 5820.143221179387
        },
        {
            "id": "E2Ri3Uudb3ogKfWBJIIhRw",
            "alias": "lokma-san-francisco",
            "name": "Lokma",
            "image_url": "https://s3-media2.fl.yelpcdn.com/bphoto/aSLeiOI6es0lXVWCb0HbqA/o.jpg",
            "is_closed": false,
            "url": "https://www.yelp.com/biz/lokma-san-francisco?adjust_creative=dMEMCWkbmi2hzr24_9J-ZA&utm_campaign=yelp_api_v3&utm_medium=api_v3_business_search&utm_source=dMEMCWkbmi2hzr24_9J-ZA",
            "review_count": 672,
            "categories": [
                {
                    "alias": "mediterranean",
                    "title": "Mediterranean"
                },
                {
                    "alias": "breakfast_brunch",
                    "title": "Breakfast & Brunch"
                },
                {
                    "alias": "vegetarian",
                    "title": "Vegetarian"
                }
            ],
            "rating": 4.5,
            "coordinates": {
                "latitude": 37.78215,
                "longitude": -122.47867
            },
            "transactions": [
                "delivery",
                "pickup"
            ],
            "price": "$$",
            "location": {
                "address1": "1801 Clement St",
                "address2": null,
                "address3": "",
                "city": "San Francisco",
                "zip_code": "94121",
                "country": "US",
                "state": "CA",
                "display_address": [
                    "1801 Clement St",
                    "San Francisco, CA 94121"
                ]
            },
            "phone": "+14157026263",
            "display_phone": "(415) 702-6263",
            "distance": 4402.2665821297205
        },
        {
            "id": "2E9O-p-lp587aOMnpLepkQ",
            "alias": "jijime-san-francisco-8",
            "name": "JIJIME",
            "image_url": "https://s3-media2.fl.yelpcdn.com/bphoto/gPimyZSIMZOG4IeYT_6i5w/o.jpg",
            "is_closed": false,
            "url": "https://www.yelp.com/biz/jijime-san-francisco-8?adjust_creative=dMEMCWkbmi2hzr24_9J-ZA&utm_campaign=yelp_api_v3&utm_medium=api_v3_business_search&utm_source=dMEMCWkbmi2hzr24_9J-ZA",
            "review_count": 570,
            "categories": [
                {
                    "alias": "korean",
                    "title": "Korean"
                },
                {
                    "alias": "asianfusion",
                    "title": "Asian Fusion"
                },
                {
                    "alias": "ramen",
                    "title": "Ramen"
                }
            ],
            "rating": 4.5,
            "coordinates": {
                "latitude": 37.7806549278456,
                "longitude": -122.478949574806
            },
            "transactions": [
                "delivery",
                "pickup"
            ],
            "price": "$$",
            "location": {
                "address1": "5524 Geary Blvd",
                "address2": "",
                "address3": null,
                "city": "San Francisco",
                "zip_code": "94121",
                "country": "US",
                "state": "CA",
                "display_address": [
                    "5524 Geary Blvd",
                    "San Francisco, CA 94121"
                ]
            },
            "phone": "+14152215353",
            "display_phone": "(415) 221-5353",
            "distance": 4333.781775165417
        },
        {
            "id": "AtFGQccBpgEZzsy9V1330Q",
            "alias": "lily-san-francisco",
            "name": "Lily",
            "image_url": "https://s3-media3.fl.yelpcdn.com/bphoto/y80_nZ_LfLw5AZip8L-MEg/o.jpg",
            "is_closed": false,
            "url": "https://www.yelp.com/biz/lily-san-francisco?adjust_creative=dMEMCWkbmi2hzr24_9J-ZA&utm_campaign=yelp_api_v3&utm_medium=api_v3_business_search&utm_source=dMEMCWkbmi2hzr24_9J-ZA",
            "review_count": 375,
            "categories": [
                {
                    "alias": "vietnamese",
                    "title": "Vietnamese"
                }
            ],
            "rating": 4.0,
            "coordinates": {
                "latitude": 37.782826,
                "longitude": -122.461686
            },
            "transactions": [
                "delivery",
                "pickup"
            ],
            "location": {
                "address1": "225 Clement St",
                "address2": null,
                "address3": null,
                "city": "San Francisco",
                "zip_code": "94118",
                "country": "US",
                "state": "CA",
                "display_address": [
                    "225 Clement St",
                    "San Francisco, CA 94118"
                ]
            },
            "phone": "+14157425285",
            "display_phone": "(415) 742-5285",
            "distance": 3299.107317666393
        }
    ],
    "total": 5100,
    "region": {
        "center": {
            "longitude": -122.43644714355469,
            "latitude": 37.76089938976322
        }
    }
}